kids/__init__.py
kids/file/__init__.py
kids/file/chk.py
kids/file/file.py
kids/file/reader.py
kids.file-0.0.7.dist-info/DESCRIPTION.rst
kids.file-0.0.7.dist-info/LICENSE.txt
kids.file-0.0.7.dist-info/METADATA
kids.file-0.0.7.dist-info/RECORD
kids.file-0.0.7.dist-info/WHEEL
kids.file-0.0.7.dist-info/metadata.json
kids.file-0.0.7.dist-info/top_level.txt
