Metadata-Version: 2.0
Name: kids.file
Version: 0.0.7
Summary: Kids file management library.
Home-page: http://github.com/0k/kids.file
Author: Valentin Lab
Author-email: valentin.lab@kalysto.org
License: BSD 3-Clause License
Platform: UNKNOWN
Classifier: Programming Language :: Python
Classifier: Intended Audience :: Developers
Classifier: License :: OSI Approved :: BSD License
Classifier: Topic :: Software Development :: Libraries :: Python Modules
Classifier: Development Status :: 5 - Production/Stable
Classifier: Topic :: Software Development :: Version Control
Classifier: Programming Language :: Python :: 2
Classifier: Programming Language :: Python :: 2.7
Classifier: Programming Language :: Python :: 3
Classifier: Programming Language :: Python :: 3.3
Classifier: Programming Language :: Python :: 3.4
Classifier: Programming Language :: Python :: 3.5
Classifier: Programming Language :: Python :: 3.6
Provides-Extra: test
Requires-Dist: minimock; extra == 'test'
Requires-Dist: nose; extra == 'test'
